coinv/__init__.py
coinv-0.0.0.dist-info/LICENSE
coinv-0.0.0.dist-info/METADATA
coinv-0.0.0.dist-info/WHEEL
coinv-0.0.0.dist-info/top_level.txt
coinv-0.0.0.dist-info/RECORD
