Metadata-Version: 2.1
Name: coinv
Version: 0.0.0
Summary: 联络：coalgo@shanshu.ai
Home-page: UNKNOWN
Author: ['coalgo@shanshu.ai']
Author-email: UNKNOWN
License: UNKNOWN
Platform: UNKNOWN
